demos/__init__.py
demos/boxdemo.py
demos/griddemo.py
demos/linegraphdemo.py
demos/scdemo.py
demos/transdemo.py
disp/__init__.py
disp/winmgr.py
widgets/XYPcmtMgr.py
widgets/__init__.py
widgets/button.py
widgets/entries.py
widgets/grid.py
widgets/linegraph.py
widgets/text.py
gamegui-1.3.1.dist-info/LICENSE.txt
gamegui-1.3.1.dist-info/METADATA
gamegui-1.3.1.dist-info/WHEEL
gamegui-1.3.1.dist-info/top_level.txt
gamegui-1.3.1.dist-info/RECORD
