Metadata-Version: 2.1
Name: gamegui
Version: 1.3.1
Summary: A widget-based pygame GUI Framework
Home-page: https://github.com/00001H/GameGui
Author: 00001H
Author-email: Programmer00001H@gmail.com
License: UNKNOWN
Project-URL: Bug Reports, https://github.com/00001H/GameGui/issues
Project-URL: Source Code, https://github.com/00001H/GameGui
Platform: UNKNOWN
Classifier: Development Status :: 4 - Beta
Classifier: Programming Language :: Python :: 3 :: Only
Classifier: Programming Language :: Python :: 3.8
Classifier: Programming Language :: Python :: 3.9
Classifier: Programming Language :: Python :: 3.10
Classifier: Topic :: Software Development :: User Interfaces
Requires-Python: >=3.8, <4
License-File: LICENSE.txt
Requires-Dist: pygame
Requires-Dist: pyperclip
